caom2/__init__.py
caom2/artifact.py
caom2/caom_util.py
caom2/checksum.py
caom2/chunk.py
caom2/common.py
caom2/diff.py
caom2/obs_reader_writer.py
caom2/observation.py
caom2/part.py
caom2/plane.py
caom2/shape.py
caom2/version.py
caom2/wcs.py
caom2/data/CAOM-2.2.xsd
caom2/data/CAOM-2.3.xsd
caom2/data/CAOM-2.4.xsd
caom2/tests/__init__.py
caom2/tests/caom_test_instances.py
caom2/tests/test_artifact.py
caom2/tests/test_caom_util.py
caom2/tests/test_checksum.py
caom2/tests/test_chunk.py
caom2/tests/test_common.py
caom2/tests/test_diffs.py
caom2/tests/test_obs_reader_writer.py
caom2/tests/test_observation.py
caom2/tests/test_part.py
caom2/tests/test_plane.py
caom2/tests/test_shape.py
caom2/tests/test_wcs.py
caom2/tests/xml_compare.py
caom2/tests/data/CompleteCompositeCircle-CAOM-2.2.xml
caom2/tests/data/CompleteCompositeCircle-CAOM-2.3.xml
caom2/tests/data/CompleteCompositePolygon-CAOM-2.2.xml
caom2/tests/data/CompleteCompositePolygon-CAOM-2.3.xml
caom2/tests/data/CompleteSimpleCircle-CAOM-2.2.xml
caom2/tests/data/CompleteSimpleCircle-CAOM-2.3.xml
caom2/tests/data/CompleteSimplePolygon-CAOM-2.2.xml
caom2/tests/data/CompleteSimplePolygon-CAOM-2.3.xml
caom2/tests/data/MinimalCompositeCircle-CAOM-2.2.xml
caom2/tests/data/MinimalCompositeCircle-CAOM-2.3.xml
caom2/tests/data/MinimalCompositePolygon-CAOM-2.2.xml
caom2/tests/data/MinimalCompositePolygon-CAOM-2.3.xml
caom2/tests/data/MinimalSimpleCircle-CAOM-2.2.xml
caom2/tests/data/MinimalSimpleCircle-CAOM-2.3.xml
caom2/tests/data/MinimalSimplePolygon-CAOM-2.2.xml
caom2/tests/data/MinimalSimplePolygon-CAOM-2.3.xml
caom2/tests/data/SampleComposite-CAOM-2.3.xml
caom2/tests/data/SampleDerived-CAOM-2.4.xml
caom2/tests/data/SampleSimple-CAOM-2.3.xml
caom2/tests/data/diff-actual-CAOM-2.3.xml
caom2/tests/data/diff-actual-CAOM-2.4.xml
caom2/tests/data/diff-expected-CAOM-2.3.xml
caom2/tests/data/diff-expected-CAOM-2.4.xml
caom2-2.6.4.dist-info/licenses/LICENSE
caom2-2.6.4.dist-info/METADATA
caom2-2.6.4.dist-info/WHEEL
caom2-2.6.4.dist-info/entry_points.txt
caom2-2.6.4.dist-info/top_level.txt
caom2-2.6.4.dist-info/RECORD
